pyproject.py
abhidrip-0.0.1.dist-info/METADATA
abhidrip-0.0.1.dist-info/WHEEL
abhidrip-0.0.1.dist-info/top_level.txt
abhidrip-0.0.1.dist-info/RECORD
