Metadata-Version: 2.4
Name: abhidrip
Version: 0.0.1
Summary: A short, one-sentence description of your package.
Author-email: Your Name <your@email.com>
Project-URL: Homepage, https://github.com/your_username/your_project
Project-URL: Bug Tracker, https://github.com/your_username/your_project/issues
Classifier: Programming Language :: Python :: 3
Classifier: License :: OSI Approved :: MIT License
Classifier: Operating System :: OS Independent
Requires-Python: >=3.8
